dash_pannellum/DashPannellum.py
dash_pannellum/__init__.py
dash_pannellum/_imports_.py
dash_pannellum/dash_pannellum.min.js
dash_pannellum/dash_pannellum.min.js.map
dash_pannellum/metadata.json
dash_pannellum/package-info.json
dash_pannellum-0.0.6.dist-info/LICENSE
dash_pannellum-0.0.6.dist-info/METADATA
dash_pannellum-0.0.6.dist-info/WHEEL
dash_pannellum-0.0.6.dist-info/top_level.txt
dash_pannellum-0.0.6.dist-info/RECORD
