Metadata-Version: 2.1
Name: dash-pannellum
Version: 0.0.6
Summary: open source panorama viewer for the web. Built using HTML5, CSS3, JavaScript, and WebGL, it is plug-in free.
Author: pip install python <pipinstallpython@gmail.com>
License: MIT
Classifier: Framework :: Dash
License-File: LICENSE
